LICENSE
MANIFEST.in
README.md
setup.cfg
setup.py
bin/cts
cts/TagScanner.py
cts/__init__.py
python_cts.egg-info/PKG-INFO
python_cts.egg-info/SOURCES.txt
python_cts.egg-info/dependency_links.txt
python_cts.egg-info/requires.txt
python_cts.egg-info/top_level.txt