Metadata-Version: 1.1
Name: python-cts
Version: 0.1.7.7
Summary: Command line ctag search
Home-page: https://github.com/Refefer/python-cts
Author: Andrew Stanton
Author-email: Andrew Stanton
License: LICENSE
Platform: UNKNOWN
Classifier: License :: OSI Approved :: Apache Software License
Classifier: Programming Language :: Python :: 2.6
Classifier: Operating System :: OS Independent
